sci_annot_eval/__init__.py
sci_annot_eval/benchmarking.py
sci_annot_eval/cli_entrypoint.py
sci_annot_eval/evaluation.py
sci_annot_eval/common/__init__.py
sci_annot_eval/common/bounding_box.py
sci_annot_eval/common/config.py
sci_annot_eval/common/prediction_field_mapper.py
sci_annot_eval/common/sci_annot_annotation.py
sci_annot_eval/exporters/__init__.py
sci_annot_eval/exporters/exporterInterface.py
sci_annot_eval/exporters/sci_annot_exporter.py
sci_annot_eval/helpers/__init__.py
sci_annot_eval/helpers/deepfigures_prediction.py
sci_annot_eval/helpers/helpers.py
sci_annot_eval/helpers/pdffigures2_page_splitter.py
sci_annot_eval/helpers/rasterize_pdfs.py
sci_annot_eval/parsers/__init__.py
sci_annot_eval/parsers/parserInterface.py
sci_annot_eval/parsers/pdffigures2_parser.py
sci_annot_eval/parsers/sci_annot_parser.py
test/__init__.py
test/test_exporters/__init__.py
test/test_exporters/sci_annot_exporter_test.py
test/test_exporters/test_exporterInterface.py
test/test_parsers/__init__.py
test/test_parsers/pdffigures2_parser_test.py
test/test_parsers/sci_annot_parser_test.py
test/test_parsers/test_parserInterface.py
sci_annot_eval-0.0.9.dist-info/LICENSE
sci_annot_eval-0.0.9.dist-info/METADATA
sci_annot_eval-0.0.9.dist-info/WHEEL
sci_annot_eval-0.0.9.dist-info/entry_points.txt
sci_annot_eval-0.0.9.dist-info/top_level.txt
sci_annot_eval-0.0.9.dist-info/RECORD
